latch_asgi-1.0.5.dist-info/METADATA
latch_asgi-1.0.5.dist-info/WHEEL
latch_asgi-1.0.5.dist-info/licenses/COPYING
latch_asgi/__init__.py
latch_asgi/asgi_iface.py
latch_asgi/auth.py
latch_asgi/config.py
latch_asgi/context/__init__.py
latch_asgi/context/common.py
latch_asgi/context/http.py
latch_asgi/context/websocket.py
latch_asgi/datadog_propagator.py
latch_asgi/framework/__init__.py
latch_asgi/framework/common.py
latch_asgi/framework/http.py
latch_asgi/framework/websocket.py
latch_asgi/py.typed
latch_asgi/server.py
latch_asgi-1.0.5.dist-info/RECORD
