Metadata-Version: 2.1
Name: latch-asgi
Version: 1.0.5
Summary: ASGI python server
Author-Email: Max Smolin <max@latch.bio>
License: CC0-1.0
Requires-Python: <4.0,>=3.11
Requires-Dist: hypercorn[uvloop]<1.0.0,>=0.14.3
Requires-Dist: latch-data-validation<1.0.0,>=0.1.3
Requires-Dist: latch-o11y<1.0.0,>=0.1.4
Requires-Dist: latch-config<1.0.0,>=0.1.6
Requires-Dist: PyJWT[crypto]<3.0.0,>=2.6.0
Requires-Dist: orjson<4.0.0,>=3.8.5
Requires-Dist: opentelemetry-sdk<2.0.0,>=1.15.0
Requires-Dist: opentelemetry-api<2.0.0,>=1.15.0
